{
  "slug": "anchoring-on-tool-capability-limits-the-mind",
  "title": "Anchoring on Tool Capability Limits the Mind",
  "summary": "A faster app or a sharper framework never moves the real ceiling, because the bottleneck was never the tool — it was the mind holding it. A short note on holding tools loosely: treating every adoption as an experiment, and walking away the moment a tool stops serving the thinking underneath.",
  "cardSummary": "A tool you cannot set down has quietly become the boundary of your thinking.",
  "date": "2026-05-27",
  "readingMinutes": 2,
  "tags": [
    "Thoughts",
    "Tools",
    "Thinking",
    "First Principles Thinking"
  ],
  "author": "Nguyen Le Phong",
  "featured": false,
  "topic": "thoughts",
  "html": "<p>It doesn&rsquo;t matter how good a tool is; the <strong>bandwidth</strong> of the brain is always the plateau you eventually hit. You can buy a faster app, adopt a sharper framework, learn a more elegant notation — and still meet the same ceiling, because the bottleneck was never the tool. It was the mind holding it.</p>\n<p>Your mind is the <strong>ultimate tool</strong>. It does come with real limitations: it <strong>decays</strong> — it needs repetition to maintain what it holds — and it is <strong>inconsistent</strong>, a side effect of its plasticity; it morphs a little every time you use it (Hebb&rsquo;s Law). Those are not flaws you can engineer away. And yet, for all of that, it remains the truest form of your thought — because it <em>is</em> your thought. No external tool can represent an idea more faithfully than the mind that grew it.</p>\n<p>So I try to hold tools loosely. Every adoption is an experiment, not a commitment. I want to stay ready to ditch a tool, or grow out of it, the moment it stops serving the thinking underneath. A tool you cannot abandon has quietly become the boundary of your thinking.</p>\n<p>The way out, when I feel myself getting attached, is to boil the tool down to first principles — the few core functions it actually performs — and weigh those against my own real workflows. Not the marketing, not what the tool <em>could</em> do; only what I actually need it to do. Adopt the function; stay free of the tool.</p>"
}
