{
  "slug": "handling-burnout-before-it-happens",
  "category": "culture",
  "title": "Handling Burnout Before It Happens",
  "summary": "A calm look at preventing burnout in engineering teams: early signals, workload visibility, recovery time, sustainable expectations, management responsibility, and the small habits that keep people from disappearing quietly.",
  "date": "2026-01-14",
  "readingMinutes": 6,
  "tags": [
    "Engineering Culture",
    "Burnout",
    "Team Health",
    "Leadership",
    "Sustainable Pace",
    "Workload"
  ],
  "author": "Nguyen Le Phong",
  "featured": false,
  "html": "<p>The office looked normal that afternoon. Keyboards were moving, calendar reminders were appearing, and someone had left a half-finished cup of tea beside a laptop. Nothing in the room looked urgent. But in a project channel, one engineer had stopped asking questions, another had started replying only at night, and a third person was quietly carrying every release risk because they were the only one who understood the old deployment script.</p>\n<p>Burnout often enters a team like that. Not as a dramatic collapse, but as a slow narrowing. People stop volunteering context. They stop pushing back on unrealistic scope. They stop learning because every free hour is used to catch up. The team still ships, so the system looks healthy from a distance. Only the people inside it can feel how expensive each normal day has become.</p>\n<p>Handling burnout before it happens requires noticing the small signals while they are still small. Late replies are not always a problem by themselves. Quietness is not always disengagement. A tired sprint is not always a broken culture. But patterns matter. When the same person always absorbs ambiguity, always handles incidents, always explains the same legacy module, or always says yes because nobody else can take the work, the team is borrowing energy from one human balance sheet.</p>\n<p>Managers and leads have a special responsibility here because burnout is rarely solved by telling people to rest. Rest helps, but if the system sends the same pressure back after Monday, the problem returns. A team needs workload visibility, not just encouragement. Who is carrying invisible support work? Who is context-switching across too many projects? Which deadlines were agreed before the real complexity was known? Which person cannot take leave without the project becoming fragile?</p>\n<p>One practical habit is to make load discussable before it becomes personal. A calm weekly review can ask what work is heavier than it looks, what is blocked by one person, what can be delayed without real damage, and what decision would reduce pressure for everyone. These questions sound simple, but they change the conversation from individual endurance to system design. The goal is not to prove that someone is struggling. The goal is to make the work easier to carry together.</p>\n<p>Another habit is to protect recovery as part of delivery, not as a reward after heroic effort. After an incident, a release, or a long stretch of unclear work, the team should not immediately fill the calendar with another urgent push. Recovery time is not laziness. It is maintenance. A codebase that never gets refactored becomes fragile. A person who never gets time to recover becomes fragile too. Both failures are predictable if we are honest.</p>\n<p>There is also a communication piece. Burnout grows faster when people feel they must perform calmness. A healthy culture lets someone say, this is too much for the current team capacity, without making them sound weak. It lets someone say, I need help with this old module, without treating that as incompetence. It lets someone say, this deadline needs a trade-off, without being labeled negative. Psychological safety is not only about code review tone. It is also about whether truth can arrive early.</p>\n<p>Preventing burnout does not mean removing all pressure. Software work has incidents, commitments, customer urgency, and seasons where the team must stretch. The difference is whether stretching becomes the default operating model. A sprint can be intense and still healthy if the team has choice, context, recovery, and a clear reason. A normal week can be damaging if it is built on silence, hidden work, and permanent urgency.</p>\n<p>I try to watch for the moment when a team starts celebrating endurance more than learning. When every story is about who stayed late, who saved the release, who carried the project alone, the culture may be training people to hide the cost. Appreciation is good, but it should lead to better systems. If one person saved the release, the next question is how to make sure they do not have to save it alone again.</p>\n<p>Burnout prevention is quiet work. It looks like clarifying scope, rotating ownership, documenting a fragile script, canceling a low-value meeting, moving one deadline, or asking one honest question before someone disappears into exhaustion. These are not glamorous actions. They are small repairs to the environment people work inside.</p>\n<p>A team does not become sustainable because everyone is endlessly resilient. It becomes sustainable when the work is shaped so resilience is not spent carelessly. If you have seen burnout prevented early, not only repaired afterward, I would be glad to hear what small signal helped the team notice in time.</p>"
}
