{
  "slug": "trust",
  "title": "Niềm tin",
  "html": "<p>Có vài &ldquo;rule of thumb&rdquo; mà tôi thấy phổ quát, áp dụng được cho nhiều ngóc ngách của đời sống. &ldquo;Mặc định là tin&rdquo; là một trong số đó.</p>\n<h3>Tại sao niềm tin quan trọng?</h3>\n<p>Nó là một <em>heuristic</em> để giải phóng dung lượng tâm trí. Thay vì xét xử lại mọi giả định, niềm tin cho bạn một nền tảng ổn định để khám phá và để xây tiếp.</p>\n<p>Và thật ra, vì không có cách nào khác để sống. Mặc định nghi ngờ mọi thứ sẽ làm bạn quá tải tới mức gãy; tâm trí đơn giản là không gánh nổi cái tải đó. Tận đáy của nó, có một lằn ranh bạn buộc phải vạch ra &mdash; và bạn &ldquo;cho lợi thế nghi ngờ&rdquo; cho nhiều thứ nằm bên kia lằn ranh đó.</p>\n<h3>Tôi tin gì?</h3>\n<ul>\n<li>Quản lý task cá nhân &mdash; tôi tin hệ thống GTD của mình.</li>\n<li>Tiến hoá một codebase &mdash; tôi tin các bộ unit test.</li>\n<li>Làm việc trong một team có tổ chức &mdash; tôi tin quy trình.</li>\n<li>Làm việc với con người &mdash; tôi mặc định tin họ.</li>\n<li>Học &mdash; tôi tin hệ SRS của mình sẽ giữ lại các facts.</li>\n</ul>\n<p>Tôi cũng tin vào triết lý âm-dương &mdash; rằng mọi quy luật đều có ngoại lệ (ngữ pháp các ngôn ngữ là ví dụ điển hình):</p>\n<ul>\n<li>Đôi khi bỏ qua chu kỳ GTD cũng ổn nếu bạn thực sự đang tận hưởng việc mình đang làm.</li>\n<li>Bạn không nên dựa vào unit test như tấm lưới an toàn duy nhất.</li>\n<li>Đừng tuân theo quy trình một cách kiêu ngạo.</li>\n<li>Có lẽ không nên giao việc quan trọng cho người lạ.</li>\n<li>Bạn nên sẵn sàng nghi ngờ những gì mình đã biết.</li>\n<li>Tôi không tin các thông tin sẽ dẫn tới một quyết định mà chưa được kiểm chứng trước.</li>\n</ul>\n<h3>Vậy chẳng phải lại về vạch xuất phát?</h3>\n<p>Vậy là ở góc của mỗi niềm tin đều có một mẩu nghi ngờ giấu sẵn. Vậy chẳng phải bài viết này về cơ bản là vô nghĩa sao?</p>\n<p>Nếu có câu trả lời dứt khoát cho việc tin một thứ hay không, cuộc đời sẽ dễ. Cũng sẽ nhàm. Đến cả nguyên tử cũng không phải bất khả phân. Có rất nhiều thành phần trong bất kỳ &ldquo;thứ&rdquo; nào: rất nhiều ý tưởng trong một cuốn sách, rất nhiều người trong một team, rất nhiều nguyên tắc trong một phương pháp luận &mdash; và niềm tin hiếm khi thuộc về tất cả chúng cùng một lúc.</p>\n<p>Chúng ta sẽ rất muốn có một góc nhìn nhất quán và toàn diện cho mọi thứ có thể được gọi gọn trong một cái tên &mdash; nhưng <a href=\"https://www.goodreads.com/quotes/103022-you-can-know-the-name-of-a-bird-in-all#:~:text=Sign%20Up%20Now-,You%20can%20know%20the%20name%20of%20a%20bird%20in%20all,of%20something%20and%20knowing%20something.\">một &ldquo;con chim&rdquo; có thật là con chim?</a> Một niềm tin bất di bất dịch một cách mù quáng là &mdash; theo lời Ralph Waldo Emerson &mdash; &ldquo;yêu tinh của những tâm trí nhỏ bé&rdquo;. Cuộc đời thú vị chính theo cách đó: một fractal vô tận để khám phá, trong đó ta không bao giờ có thể tuyệt đối tin rằng mình đúng. <em>(Một mạch suy nghĩ tôi đã san sẻ cùng <a href=\"https://huylenq.github.io\" target=\"_blank\" rel=\"noopener noreferrer\">vườn ý nghĩ của một người bạn</a>.)</em></p>\n<hr>\n<ul>\n<li><a href=\"/thoughts/programmable-self\">Bản thân có thể lập trình</a></li>\n</ul>",
  "backlinks": [],
  "maturity": "evergreen"
}
